fakesnow/__init__.py
fakesnow/__main__.py
fakesnow/arrow.py
fakesnow/checks.py
fakesnow/cli.py
fakesnow/conn.py
fakesnow/converter.py
fakesnow/copy_into.py
fakesnow/cursor.py
fakesnow/expr.py
fakesnow/fakes.py
fakesnow/fixtures.py
fakesnow/info_schema.py
fakesnow/instance.py
fakesnow/logger.py
fakesnow/macros.py
fakesnow/pandas_tools.py
fakesnow/params.py
fakesnow/py.typed
fakesnow/rowtype.py
fakesnow/server.py
fakesnow/variables.py
fakesnow/transforms/__init__.py
fakesnow/transforms/ddl.py
fakesnow/transforms/merge.py
fakesnow/transforms/show.py
fakesnow/transforms/stage.py
fakesnow/transforms/transforms.py
fakesnow-0.11.1.dist-info/licenses/LICENSE
tools/decode.py
fakesnow-0.11.1.dist-info/METADATA
fakesnow-0.11.1.dist-info/WHEEL
fakesnow-0.11.1.dist-info/entry_points.txt
fakesnow-0.11.1.dist-info/top_level.txt
fakesnow-0.11.1.dist-info/RECORD
