Metadata-Version: 2.4
Name: fakesnow
Version: 0.11.1
Summary: Fake Snowflake Connector for Python. Run, mock and test Snowflake DB locally.
License:                                  Apache License
Project-URL: Source, https://github.com/tekumara/fakesnow
Project-URL: Changelog, https://github.com/tekumara/fakesnow/blob/main/CHANGELOG.md
Keywords: snowflake,snowflakedb,fake,local,mock,testing
Classifier: License :: OSI Approved :: MIT License
Requires-Python: >=3.10
License-File: LICENSE
Requires-Dist: duckdb~=1.4.1
Requires-Dist: pyarrow
Requires-Dist: snowflake-connector-python
Requires-Dist: sqlglot~=28.5.0
Provides-Extra: server
Requires-Dist: starlette; extra == "server"
Requires-Dist: uvicorn; extra == "server"
Dynamic: license-file
